setup.cfg
setup.py
apns23/__init__.py
apns23/client.py
apns23/credentials.py
apns23/errors.py
apns23/payload.py
apns23.egg-info/PKG-INFO
apns23.egg-info/SOURCES.txt
apns23.egg-info/dependency_links.txt
apns23.egg-info/requires.txt
apns23.egg-info/top_level.txt
test/test_client.py
test/test_credentials.py
test/test_payload.py