Metadata-Version: 1.1
Name: apns23
Version: 1.0.1
Summary: A python library for interacting with the Apple Push Notification Service via HTTP/2 protocol
Home-page: https://github.com/VinayGValsaraj/PyAPNs23
Author: Vinay Valsaraj
Author-email: vinaygvalsaraj@gmail.com
License: MIT
Platform: UNKNOWN
Classifier: Development Status :: 4 - Beta
Classifier: License :: OSI Approved :: MIT License
Classifier: Programming Language :: Python :: 2.7
Classifier: Programming Language :: Python :: 3.6
Classifier: Topic :: Software Development :: Libraries
